{
  "project_info": {
    "project_number": "967094561686",
    "project_id": "mynotes-flutter-lorena",
    "storage_bucket": "mynotes-flutter-lorena.appspot.com"
  },
  "client": [
    {
      "client_info": {
        "mobilesdk_app_id": "1:967094561686:android:64b549fcc4468df4140bb7",
        "android_client_info": {
          "package_name": "com.FirstProject.mynotes"
        }
      },
      "oauth_client": [
        {
          "client_id": "967094561686-hupcn77dt594nniuh85vptnjqhqoph74.apps.googleusercontent.com",
          "client_type": 3
        }
      ],
      "api_key": [
        {
          "current_key": "AIzaSyCDWjaVsxs_BMQKLF2RkNgrRD4YMnTsoLQ"
        }
      ],
      "services": {
        "appinvite_service": {
          "other_platform_oauth_client": [
            {
              "client_id": "967094561686-hupcn77dt594nniuh85vptnjqhqoph74.apps.googleusercontent.com",
              "client_type": 3
            }
          ]
        }
      }
    }
  ],
  "configuration_version": "1"
}